[
  {
    "_id": "Titanic-ML",
    "_type": "dashboard",
    "_source": {
      "title": "Titanic ML",
      "hits": 0,
      "description": "",
      "panelsJSON": "[{\"col\":1,\"id\":\"Titanic-:-barplot-age\",\"panelIndex\":1,\"row\":9,\"size_x\":4,\"size_y\":3,\"type\":\"visualization\"},{\"col\":9,\"id\":\"Titanic-:-count-passagers\",\"panelIndex\":2,\"row\":1,\"size_x\":4,\"size_y\":4,\"type\":\"visualization\"},{\"col\":9,\"id\":\"Titanic-:-piechart-sex\",\"panelIndex\":3,\"row\":9,\"size_x\":4,\"size_y\":3,\"type\":\"visualization\"},{\"col\":5,\"id\":\"Titanic-:-piechart-Pclass\",\"panelIndex\":4,\"row\":9,\"size_x\":4,\"size_y\":3,\"type\":\"visualization\"},{\"col\":1,\"id\":\"Titanic-:-barplot-survived- -prediction\",\"panelIndex\":5,\"row\":1,\"size_x\":8,\"size_y\":4,\"type\":\"visualization\"},{\"col\":5,\"id\":\"Titanic-:-barplot-survived- -prediction- -Pclass\",\"panelIndex\":6,\"row\":5,\"size_x\":4,\"size_y\":4,\"type\":\"visualization\"},{\"col\":9,\"id\":\"Titanic-:-barplot-survived- -prediction- -Sex\",\"panelIndex\":7,\"row\":5,\"size_x\":4,\"size_y\":4,\"type\":\"visualization\"},{\"col\":1,\"id\":\"Titanic-:-barplot-survived- -prediction- -Age\",\"panelIndex\":8,\"row\":5,\"size_x\":4,\"size_y\":4,\"type\":\"visualization\"}]",
      "optionsJSON": "{\"darkTheme\":false}",
      "uiStateJSON": "{}",
      "version": 1,
      "timeRestore": false,
      "kibanaSavedObjectMeta": {
        "searchSourceJSON": "{\"filter\":[{\"query\":{\"query_string\":{\"analyze_wildcard\":true,\"query\":\"*\"}}}]}"
      }
    }
  }
]